pyawsopstoolkit_validators/__globals__.py
pyawsopstoolkit_validators/__init__.py
pyawsopstoolkit_validators/__validations__.py
pyawsopstoolkit_validators/account_validator.py
pyawsopstoolkit_validators/arn_validator.py
pyawsopstoolkit_validators/exceptions.py
pyawsopstoolkit_validators/policy_validator.py
pyawsopstoolkit_validators/region_validator.py
pyawsopstoolkit_validators/tag_validator.py
pyawsopstoolkit_validators-0.1.0.dist-info/LICENSE
pyawsopstoolkit_validators-0.1.0.dist-info/METADATA
pyawsopstoolkit_validators-0.1.0.dist-info/WHEEL
pyawsopstoolkit_validators-0.1.0.dist-info/top_level.txt
pyawsopstoolkit_validators-0.1.0.dist-info/RECORD
