Metadata-Version: 2.1
Name: pyawsopstoolkit-validators
Version: 0.1.0
Summary: This package provides a comprehensive set of validation classes specifically crafted for use with AWS (Amazon Web
Home-page: https://github.com/coldsofttech/pyawsopstoolkit-validators.git
Author: coldsofttech
License: MIT
Keywords: aws,toolkit,operations,tools,development,python,validation,utilities,amazon-web-services
Classifier: Development Status :: 4 - Beta
Classifier: Intended Audience :: Developers
Classifier: Topic :: Software Development :: Libraries
Classifier: Topic :: Software Development :: Libraries :: Python Modules
Classifier: License :: OSI Approved :: MIT License
Classifier: Programming Language :: Python :: 3.10
Classifier: Programming Language :: Python :: 3.11
Classifier: Programming Language :: Python :: 3.12
License-File: LICENSE
